python_with_rust-0.1.5.dist-info/METADATA
python_with_rust-0.1.5.dist-info/WHEEL
python_with_rust/__init__.py
python_with_rust/python_with_rust.cpython-38-darwin.so
python_with_rust-0.1.5.dist-info/RECORD
