Metadata-Version: 2.3
Name: python_with_rust
Version: 0.1.5
Classifier: Programming Language :: Rust
Classifier: Programming Language :: Python :: Implementation :: CPython
Classifier: Programming Language :: Python :: Implementation :: PyPy
Summary: Python 调用 Rust 的示例
Keywords: rust,pyo3,python,performance,hybrid
Author-email: Guo Fei <me@guofei.site>
License: MIT
Requires-Python: >=3.8
